{
  "notes": [
    {
      "title": "Druhá poznámka 2",
      "description": "Popis 2",
      "category": "In progress",
      "date": "2023-10-29T15:57:21.445Z",
      "id": "59ca6508-2b46-4517-aca4-ed51906b30ef"
    },
    {
      "id": "8cd4a5c2-e704-4abc-a0c5-df6c710c0d33",
      "title": "Testing",
      "description": "Completed",
      "category": "Completed",
      "date": "2023-10-25T17:16:30.457Z"
    },
    {
      "id": "3c13d13d-5941-464c-9870-9e0e75259758",
      "title": "Lorem ipsum",
      "description": "Lorem ipsum dolor sit amet, consectetur adipiscing elit. Phasellus et mi tincidunt, egestas dolor nec, ultrices neque. Nam vel viverra arcu, a feugiat felis. Curabitur sodales nisl ac libero aliquet l",
      "category": "In progress",
      "date": "2023-10-26T16:40:56.760Z"
    },
    {
      "id": "dxsGUmh",
      "title": "Archived",
      "description": "Archived",
      "category": "Archived",
      "date": "2023-10-29T17:33:54.920Z"
    }
  ]
}